calculate/__init__.py
calculate/calc.py
calculate/unit_tests.py
ishay_calculate_application-0.0.1.dist-info/METADATA
ishay_calculate_application-0.0.1.dist-info/WHEEL
ishay_calculate_application-0.0.1.dist-info/top_level.txt
ishay_calculate_application-0.0.1.dist-info/RECORD
