Metadata-Version: 2.1
Name: ishay-calculate-application
Version: 0.0.1
Summary: A sample Python project for calculations
Home-page: https://github.com/naturalett/getting-started
License: UNKNOWN
Platform: UNKNOWN
Requires-Dist: xmlrunner
